pytest_texts_score/__init__.py
pytest_texts_score/_helper.py
pytest_texts_score/api.py
pytest_texts_score/api_wrappers.py
pytest_texts_score/client.py
pytest_texts_score/communication.py
pytest_texts_score/evaluate_score.py
pytest_texts_score/plugin.py
pytest_texts_score/prompts.py
pytest_texts_score-1.0.1.dist-info/licenses/LICENSE
pytest_texts_score-1.0.1.dist-info/METADATA
pytest_texts_score-1.0.1.dist-info/WHEEL
pytest_texts_score-1.0.1.dist-info/entry_points.txt
pytest_texts_score-1.0.1.dist-info/top_level.txt
pytest_texts_score-1.0.1.dist-info/RECORD
