Metadata-Version: 2.4
Name: pytest-texts-score
Version: 1.0.1
Summary: Texts content similarity scoring plugin
Author-email: Patrik Vodila <vodilpat@cvut.fit.cz>
Maintainer-email: Patrik Vodila <vodilpat@cvut.fit.cz>
License: 
Project-URL: Repository, https://github.com/VodilaPat/pytest-texts-score
Classifier: Framework :: Pytest
Classifier: Development Status :: 4 - Beta
Classifier: Intended Audience :: Developers
Classifier: Topic :: Software Development :: Testing
Classifier: Operating System :: OS Independent
Classifier: Programming Language :: Python
Classifier: Programming Language :: Python :: 3.10
Classifier: Programming Language :: Python :: 3.11
Classifier: Programming Language :: Python :: 3.12
Classifier: Programming Language :: Python :: 3 :: Only
Classifier: Programming Language :: Python :: Implementation :: CPython
Classifier: Programming Language :: Python :: Implementation :: PyPy
Classifier: License :: OSI Approved :: MIT License
Requires-Python: <4.0.0,>=3.10
License-File: LICENSE
Requires-Dist: pytest>=8.4.2
Requires-Dist: requests<3.0.0,>=2.32.5
Requires-Dist: langchain-openai==0.3.14
Dynamic: license-file
